{
"Darkbishop Benedictus": {
    "atk": 5,
    "cdn": "https://cdn.hearthstonetopdecks.com/wp-content/uploads/2021/07/Darkbishop-Benedictus-300x428.png",
    "class": "PR",
    "cost": 5,
    "desc": "Start of Game: If the spells in your deck are all Shadow, enter Shadowform.",
    "head": "darkbishop-benedictus",
    "hp": 6,
    "hpwn": 12288,
    "name": "Darkbishop Benedictus",
    "rarity": "Legendary",
    "set": "United in Stormwind",
    "subType": null,
    "type": "Minion"
},
"Elekk Mount": {
    "atk": null,
    "cdn": "https://cdn.hearthstonetopdecks.com/wp-content/uploads/2021/07/Elekk-Mount-300x424.png",
    "class": "PR",
    "cost": 7,
    "desc": "Give a minion +4/+7 and Taunt . When it dies, summon an Elekk.",
    "head": "elekk-mount",
    "hp": null,
    "hpwn": 12288,
    "name": "Elekk Mount",
    "rarity": "Rare",
    "set": "United in Stormwind",
    "subType": null,
    "type": "Spell"
},
"Fire Sale": {
    "atk": null,
    "cdn": "https://cdn.hearthstonetopdecks.com/wp-content/uploads/2021/07/Fire-Sale-300x425.png",
    "class": "MA",
    "cost": 4,
    "desc": "Tradeable Deal 3 damage to all minions.",
    "head": "fire-sale",
    "hp": null,
    "hpwn": 12288,
    "name": "Fire Sale",
    "rarity": "Common",
    "set": "United in Stormwind",
    "subType": null,
    "type": "Spell"
},
"Flightmaster Dungar": {
    "atk": 3,
    "cdn": "https://cdn.hearthstonetopdecks.com/wp-content/uploads/2021/07/Flightmaster-Dungar-300x428.png",
    "class": "N",
    "cost": 3,
    "desc": "Battlecry: Choose a flightpath and go Dormant . Awaken with a bonus when you complete it!",
    "head": "flightmaster-dungar",
    "hp": 3,
    "hpwn": 12288,
    "name": "Flightmaster Dungar",
    "rarity": "Legendary",
    "set": "United in Stormwind",
    "subType": null,
    "type": "Minion"
},
"Heavy Plate": {
    "atk": null,
    "cdn": "https://cdn.hearthstonetopdecks.com/wp-content/uploads/2021/07/Heavy-Plate-300x424.png",
    "class": "WR",
    "cost": 3,
    "desc": "Tradeable Gain 8 Armor.",
    "head": "heavy-plate",
    "hp": null,
    "hpwn": 12288,
    "name": "Heavy Plate",
    "rarity": "Common",
    "set": "United in Stormwind",
    "subType": null,
    "type": "Spell"
},
"Impatient Shopkeep": {
    "atk": 3,
    "cdn": "https://cdn.hearthstonetopdecks.com/wp-content/uploads/2021/07/Impatient-Shopkeep-300x416.png",
    "class": "N",
    "cost": 3,
    "desc": "Tradeable  Rush",
    "head": "impatient-shopkeep",
    "hp": 3,
    "hpwn": 12288,
    "name": "Impatient Shopkeep",
    "rarity": "Common",
    "set": "United in Stormwind",
    "subType": null,
    "type": "Minion"
},
"Mailbox Dancer": {
    "atk": 3,
    "cdn": "https://cdn.hearthstonetopdecks.com/wp-content/uploads/2021/07/Mailbox-Dancer-300x416.png",
    "class": "N",
    "cost": 2,
    "desc": "Battlecry: Add a Coin to your hand. Deathrattle: Give your opponent one.",
    "head": "mailbox-dancer",
    "hp": 2,
    "hpwn": 12288,
    "name": "Mailbox Dancer",
    "rarity": "Rare",
    "set": "United in Stormwind",
    "subType": null,
    "type": "Minion"
},
"Pandaren Importer": {
    "atk": 1,
    "cdn": "https://cdn.hearthstonetopdecks.com/wp-content/uploads/2021/07/Pandaren-Importer-300x416.png",
    "class": "N",
    "cost": 2,
    "desc": "Battlecry: Discover a spell that didn't start in your deck.",
    "head": "pandaren-importer",
    "hp": 3,
    "hpwn": 12288,
    "name": "Pandaren Importer",
    "rarity": "Common",
    "set": "United in Stormwind",
    "subType": null,
    "type": "Minion"
},
"Peasant": {
    "atk": 2,
    "cdn": "https://cdn.hearthstonetopdecks.com/wp-content/uploads/2021/07/Peasant-300x416.png",
    "class": "N",
    "cost": 1,
    "desc": "At the start of your turn, draw a card.",
    "head": "peasant",
    "hp": 1,
    "hpwn": 12288,
    "name": "Peasant",
    "rarity": "Common",
    "set": "United in Stormwind",
    "subType": null,
    "type": "Minion"
},
"Prismatic Jewel Kit": {
    "atk": 0,
    "cdn": "https://cdn.hearthstonetopdecks.com/wp-content/uploads/2021/07/Prismatic-Jewel-Kit-300x413.png",
    "class": "PL",
    "cost": 1,
    "desc": "After a friendly minion loses Divine Shield , give minions in your hand +1/+1. Lose 1 Durability.",
    "head": "prismatic-jewel-kit",
    "hp": 3,
    "hpwn": 12288,
    "name": "Prismatic Jewel Kit",
    "rarity": "Rare",
    "set": "United in Stormwind",
    "subType": null,
    "type": "Weapon"
},
"Ramming Mount": {
    "atk": null,
    "cdn": "https://cdn.hearthstonetopdecks.com/wp-content/uploads/2021/07/Ramming-Mount-300x424.png",
    "class": "HT",
    "cost": 3,
    "desc": "Give a minion +2/+2 and Immune while attacking. When it dies, summon a Ram.",
    "head": "ramming-mount",
    "hp": null,
    "hpwn": 12288,
    "name": "Ramming Mount",
    "rarity": "Rare",
    "set": "United in Stormwind",
    "subType": null,
    "type": "Spell"
},
"Runed Mithril Rod": {
    "atk": 0,
    "cdn": "https://cdn.hearthstonetopdecks.com/wp-content/uploads/2021/07/Runed-Mithril-Rod-300x413.png",
    "class": "WL",
    "cost": 3,
    "desc": "After you draw 4 cards, reduce the Cost of cards in your hand by (1). Lose 1 Durability.",
    "head": "runed-mithril-rod",
    "hp": 2,
    "hpwn": 12288,
    "name": "Runed Mithril Rod",
    "rarity": "Rare",
    "set": "United in Stormwind",
    "subType": null,
    "type": "Weapon"
},
"Rustrot Viper": {
    "atk": 3,
    "cdn": "https://cdn.hearthstonetopdecks.com/wp-content/uploads/2021/07/Rustrot-Viper-300x416.png",
    "class": "N",
    "cost": 3,
    "desc": "Tradeable  Battlecry: Destroy your opponent's weapon.",
    "head": "rustrot-viper",
    "hp": 4,
    "hpwn": 12288,
    "name": "Rustrot Viper",
    "rarity": "Common",
    "set": "United in Stormwind",
    "subType": "Beast",
    "type": "Minion"
},
"Sorcerer's Gambit": {
    "atk": null,
    "cdn": "https://cdn.hearthstonetopdecks.com/wp-content/uploads/2021/07/Sorcerers-Gambit-300x385.png",
    "class": "MA",
    "cost": 1,
    "desc": "Questline: Cast a Fire, Frost and Arcane spell. Reward: Draw a spell.",
    "head": "sorcerers-gambit",
    "hp": null,
    "hpwn": 12288,
    "name": "Sorcerer's Gambit",
    "rarity": "Legendary",
    "set": "United in Stormwind",
    "subType": null,
    "type": "Spell"
},
"Spice Bread Baker": {
    "atk": 3,
    "cdn": "https://cdn.hearthstonetopdecks.com/wp-content/uploads/2021/07/Spice-Bread-Baker-300x419.png",
    "class": "N",
    "cost": 4,
    "desc": "Battlecry: Restore Health to your hero equal to your hand size.",
    "head": "spice-bread-baker",
    "hp": 2,
    "hpwn": 12288,
    "name": "Spice Bread Baker",
    "rarity": "Common",
    "set": "United in Stormwind",
    "subType": null,
    "type": "Minion"
},
"The Demon Seed": {
    "atk": null,
    "cdn": "https://cdn.hearthstonetopdecks.com/wp-content/uploads/2021/07/The-Demon-Seed-300x385.png",
    "class": "WL",
    "cost": 1,
    "desc": "Questline: Take 6 damage on your turns. Reward: Lifesteal. Deal 3 damage to the enemy hero.",
    "head": "the-demon-seed",
    "hp": null,
    "hpwn": 12288,
    "name": "The Demon Seed",
    "rarity": "Legendary",
    "set": "United in Stormwind",
    "subType": null,
    "type": "Spell"
},
"Touch of the Nathrezim": {
    "atk": null,
    "cdn": "https://cdn.hearthstonetopdecks.com/wp-content/uploads/2021/07/Touch-of-the-Nathrezim-300x424.png",
    "class": "WL",
    "cost": 1,
    "desc": "Deal 2 damage to a minion. If it dies, restore 4 Health to your hero.",
    "head": "touch-of-the-nathrezim",
    "hp": null,
    "hpwn": 12288,
    "name": "Touch of the Nathrezim",
    "rarity": "Rare",
    "set": "United in Stormwind",
    "subType": null,
    "type": "Spell"
}
}